zeroArm_sdk/__init__.py
zeroArm_sdk/_core.cpython-311-aarch64-linux-musl.so
zeroArm_sdk/arm.py
zeroArm_sdk/arm_types.py
zeroArm_sdk/exceptions.py
zeroArm_sdk/locale/zh_CN/LC_MESSAGES/zeroArm_sdk.mo
zeroarm_sdk-0.1.0.dist-info/METADATA
zeroarm_sdk-0.1.0.dist-info/WHEEL
zeroarm_sdk-0.1.0.dist-info/top_level.txt
zeroarm_sdk-0.1.0.dist-info/RECORD
zeroarm_sdk-0.1.0.dist-info/licenses/LICENSE.txt
