Metadata-Version: 2.1
Name: zeroArm_sdk
Version: 0.1.0
Summary: Official SDK for ZeroArm robotic arm (proprietary)
Author: ForceEase Co.
Author-email: support@forceease.tech
License: MIT License
Requires-Python: >=3.8
License-File: LICENSE.txt
Requires-Dist: pyzmq>=25.0
Requires-Dist: websockets
Requires-Dist: zeroconf
Requires-Dist: tqdm
